MANIFEST.in
README.txt
setup.py
docs/HISTORY.txt
docs/LICENSE.txt
silvatheme/__init__.py
silvatheme.silvadocs.egg-info/PKG-INFO
silvatheme.silvadocs.egg-info/SOURCES.txt
silvatheme.silvadocs.egg-info/dependency_links.txt
silvatheme.silvadocs.egg-info/namespace_packages.txt
silvatheme.silvadocs.egg-info/not-zip-safe
silvatheme.silvadocs.egg-info/requires.txt
silvatheme.silvadocs.egg-info/top_level.txt
silvatheme/silvadocs/__init__.py
silvatheme/silvadocs/configure.zcml
silvatheme/silvadocs/silvadocs.py
silvatheme/silvadocs/silvadocs_templates/layout.cpt
silvatheme/silvadocs/static/default.css
silvatheme/silvadocs/static/default.min.css
silvatheme/silvadocs/static/favicon.ico
silvatheme/silvadocs/static/html5reset.css
silvatheme/silvadocs/static/html5reset.min.css
silvatheme/silvadocs/static/license.txt
silvatheme/silvadocs/static/modernizr-1.7.min.js
silvatheme/silvadocs/static/typography.css
silvatheme/silvadocs/static/typography.min.css
silvatheme/silvadocs/static/images/backup.png
silvatheme/silvadocs/static/images/bullet_triangle_green.png
silvatheme/silvadocs/static/images/bullet_triangle_toggled.png
silvatheme/silvadocs/static/images/external.png
silvatheme/silvadocs/static/images/favicon.ico
silvatheme/silvadocs/static/images/img01.gif
silvatheme/silvadocs/static/images/img02.gif
silvatheme/silvadocs/static/images/img03.gif
silvatheme/silvadocs/static/images/img04.jpg
silvatheme/silvadocs/static/images/img05.gif
silvatheme/silvadocs/static/images/img06.gif
silvatheme/silvadocs/static/images/img07.gif
silvatheme/silvadocs/static/images/img08.gif
silvatheme/silvadocs/static/images/img09.gif
silvatheme/silvadocs/static/images/img10.gif
silvatheme/silvadocs/static/images/site_bg.png
silvatheme/silvadocs/static/images/spacer.gif
silvatheme/silvadocs/static/images/upalevel.png