Metadata-Version: 1.1
Name: silvatheme.silvadocs
Version: 1.0.2
Summary: Silva Docs theme for Silva CMS
Home-page: https://github.com/silvacms/silvatheme.silvadocs
Author: Infrae
Author-email: info@infrae.com
License: BSD and Creative Commons
Keywords: silvatheme silvadocs
Platform: UNKNOWN
Classifier: Framework :: Zope2
Classifier: License :: OSI Approved :: BSD License
Classifier: Programming Language :: Python
Classifier: Topic :: Software Development :: Libraries :: Python Modules
